datasets/get_profiles.py
datasets/ingest_chat_dataset.py
lindormmemobase/__init__.py
lindormmemobase/main.py
lindormmemobase/config/__init__.py
lindormmemobase/config/color.py
lindormmemobase/config/config.py
lindormmemobase/config/project_logger.py
lindormmemobase/core/__init__.py
lindormmemobase/core/constants.py
lindormmemobase/core/extraction/__init__.py
lindormmemobase/core/extraction/processor/__init__.py
lindormmemobase/core/extraction/processor/entry_summary.py
lindormmemobase/core/extraction/processor/event_summary.py
lindormmemobase/core/extraction/processor/extract.py
lindormmemobase/core/extraction/processor/merge.py
lindormmemobase/core/extraction/processor/organize.py
lindormmemobase/core/extraction/processor/process_blobs.py
lindormmemobase/core/extraction/processor/profile_events.py
lindormmemobase/core/extraction/processor/summary.py
lindormmemobase/core/extraction/prompts/__init__.py
lindormmemobase/core/extraction/prompts/chat_context_pack.py
lindormmemobase/core/extraction/prompts/event_tagging.py
lindormmemobase/core/extraction/prompts/extract_profile.py
lindormmemobase/core/extraction/prompts/merge_events.py
lindormmemobase/core/extraction/prompts/merge_profile.py
lindormmemobase/core/extraction/prompts/organize_profile.py
lindormmemobase/core/extraction/prompts/pick_related_profiles.py
lindormmemobase/core/extraction/prompts/profile_init_utils.py
lindormmemobase/core/extraction/prompts/router.py
lindormmemobase/core/extraction/prompts/summary_chats.py
lindormmemobase/core/extraction/prompts/summary_entry_chats.py
lindormmemobase/core/extraction/prompts/summary_profile.py
lindormmemobase/core/extraction/prompts/user_profile_topics.py
lindormmemobase/core/extraction/prompts/utils.py
lindormmemobase/core/extraction/prompts/zh_extract_profile.py
lindormmemobase/core/extraction/prompts/zh_merge_events.py
lindormmemobase/core/extraction/prompts/zh_merge_profile.py
lindormmemobase/core/extraction/prompts/zh_summary_entry_chats.py
lindorm_memobase-0.2.3.1.dist-info/METADATA
lindorm_memobase-0.2.3.1.dist-info/WHEEL
lindorm_memobase-0.2.3.1.dist-info/top_level.txt
lindorm_memobase-0.2.3.1.dist-info/RECORD
