Metadata-Version: 2.4
Name: lindorm-memobase
Version: 0.2.3.1
Summary: A lightweight memory extraction and profile management system for LLM applications
Author: LindormMemobase Team
License: MIT
Keywords: llm,memory,embedding,profile,extraction
Classifier: Development Status :: 3 - Alpha
Classifier: Intended Audience :: Developers
Classifier: License :: OSI Approved :: MIT License
Classifier: Programming Language :: Python :: 3.11
Classifier: Programming Language :: Python :: 3.12
Classifier: Topic :: Software Development :: Libraries :: Python Modules
Requires-Python: >=3.11
Requires-Dist: python-dotenv>=1.0.0
Requires-Dist: openai>=1.98.0
Requires-Dist: pydantic>=2.11.7
Requires-Dist: pyyaml>=6.0.2
Requires-Dist: tiktoken>=0.9.0
Requires-Dist: typeguard>=4.4.4
Requires-Dist: opensearch-py>=2.0.0
Requires-Dist: mysql-connector-python==8.0.11
Requires-Dist: numpy
Provides-Extra: dev
Requires-Dist: pytest>=8.0; extra == "dev"
Requires-Dist: pytest-asyncio>=0.21.0; extra == "dev"
Requires-Dist: pytest-cov>=4.0.0; extra == "dev"
